ksuit/__init__.py
ksuit/core/__init__.py
ksuit/core/callbacks/__init__.py
ksuit/core/callbacks/callback.py
ksuit/core/callbacks/metric_callback.py
ksuit/core/callbacks/periodic_callback.py
ksuit/core/checkpoint_converters/__init__.py
ksuit/core/checkpoint_converters/checkpoint_converter.py
ksuit/core/collators/__init__.py
ksuit/core/collators/batch_processor.py
ksuit/core/collators/collator.py
ksuit/core/collators/sample_processor.py
ksuit/core/collators/samples_to_batch_processor.py
ksuit/core/datasets/__init__.py
ksuit/core/datasets/dataset.py
ksuit/core/datasets/dummy_dataset.py
ksuit/core/datasets/select_items_wrapper.py
ksuit/core/datasets/subset.py
ksuit/core/datasets/wrapper.py
ksuit/core/factories/__init__.py
ksuit/core/factories/factory.py
ksuit/core/factories/optimizer_factory.py
ksuit/core/factories/schedule_factory.py
ksuit/core/initializers/__init__.py
ksuit/core/initializers/initializer.py
ksuit/core/initializers/resume_initializer.py
ksuit/core/initializers/sequential_parameter_initializer.py
ksuit/core/initializers/single_parameter_initializer.py
ksuit/core/loss_wrappers/__init__.py
ksuit/core/loss_wrappers/loss_wrapper.py
ksuit/core/models/__init__.py
ksuit/core/models/model.py
ksuit/core/models/torch_to_ksuit_model_wrapper.py
ksuit/core/optim/__init__.py
ksuit/core/optim/lr_schedule.py
ksuit/core/optim/optimizer.py
ksuit/core/optim/param_group_modifier.py
ksuit/core/parameter_renamers/__init__.py
ksuit/core/parameter_renamers/parameter_renamer.py
ksuit/core/providers/__init__.py
ksuit/core/providers/data_provider.py
ksuit/core/providers/distributed_provider.py
ksuit/core/providers/num_workers_provider.py
ksuit/core/providers/path_provider.py
ksuit/core/providers/training_progress_provider.py
ksuit/core/runners/__init__.py
ksuit/core/runners/runner.py
ksuit/core/samplers/__init__.py
ksuit/core/samplers/interleaved_sampler.py
ksuit/core/schedules/__init__.py
ksuit/core/schedules/schedule.py
ksuit/core/schedules/schedule_postprocessor.py
ksuit-0.0.1.dist-info/licenses/LICENSE
ksuit-0.0.1.dist-info/METADATA
ksuit-0.0.1.dist-info/WHEEL
ksuit-0.0.1.dist-info/top_level.txt
ksuit-0.0.1.dist-info/RECORD
