Metadata-Version: 2.4
Name: ksuit
Version: 0.0.1
Summary: ksuit
Classifier: Programming Language :: Python :: 3
Classifier: License :: OSI Approved :: MIT License
Classifier: Operating System :: OS Independent
Requires-Python: >=3.12
License-File: LICENSE
Requires-Dist: torch
Dynamic: license-file
